commands/__init__.py
commands/devutils.py
commands/dockertools.py
commands/helpers.py
commands/sshutils.py
power_user_tools-0.1.8.data/scripts/dtimg
power_user_tools-0.1.8.data/scripts/dtip
power_user_tools-0.1.8.data/scripts/dtnet
power_user_tools-0.1.8.data/scripts/dtports
power_user_tools-0.1.8.data/scripts/dtrestart
power_user_tools-0.1.8.data/scripts/dtrm
power_user_tools-0.1.8.data/scripts/dtstart
power_user_tools-0.1.8.data/scripts/dtstop
power_user_tools-0.1.8.data/scripts/ktclean
power_user_tools-0.1.8.data/scripts/ktdeploy
power_user_tools-0.1.8.data/scripts/ktinitbash
power_user_tools-0.1.8.data/scripts/ktls
power_user_tools-0.1.8.data/scripts/ktns
power_user_tools-0.1.8.data/scripts/ktpods
power_user_tools-0.1.8.data/scripts/xpgrmhistory
power_user_tools-0.1.8.data/scripts/xppr
power_user_tools-0.1.8.data/scripts/xprandpw
power_user_tools-0.1.8.dist-info/LICENSE
power_user_tools-0.1.8.dist-info/METADATA
power_user_tools-0.1.8.dist-info/WHEEL
power_user_tools-0.1.8.dist-info/entry_points.txt
power_user_tools-0.1.8.dist-info/top_level.txt
power_user_tools-0.1.8.dist-info/RECORD
