Metadata-Version: 2.1
Name: power-user-tools
Version: 0.1.8
Summary: Power User Tools make your life so much easier
Home-page: https://github.com/dameyerdave/power-user-tools
Author: dameyerdave
Author-email: dameyerdave@gmail.com
License: MIT
Keywords: power user tools ssh sshd reverse tunnel docker easy development
Classifier: Programming Language :: Python :: 3
Classifier: License :: OSI Approved :: MIT License
Classifier: Operating System :: OS Independent
License-File: LICENSE
Requires-Dist: click (==8.1.3)
Requires-Dist: python-dotenv (==0.21.0)
Requires-Dist: friendlylog (==1.0.2)
Requires-Dist: yachalk (==0.1.5)
Requires-Dist: rich (==12.6.0)
Requires-Dist: sh (==2.0.6)
